crystallite_size_calculator/__init__.py
crystallite_size_calculator/crystallite_size.py
crystallite_size_calculator/envelope_function_approach.py
crystallite_size_calculator/filetyper.py
crystallite_size_calculator/strain_calculator.py
crystallite_size_calculator/xrd_calculator.py
crystallite_size_calculator-0.1.0.dist-info/METADATA
crystallite_size_calculator-0.1.0.dist-info/WHEEL
crystallite_size_calculator-0.1.0.dist-info/RECORD
