Metadata-Version: 2.1
Name: crystallite-size-calculator
Version: 0.1.0
Summary: 
Author: Dinga Wonanke
Author-email: bafgreat@gmail.com
Requires-Python: >=3.10,<4.0
Classifier: Programming Language :: Python :: 3
Classifier: Programming Language :: Python :: 3.10
Classifier: Programming Language :: Python :: 3.11
Classifier: Programming Language :: Python :: 3.12
Requires-Dist: ase (>=3.23.0,<4.0.0)
Requires-Dist: mkdocs (>=1.6.1,<2.0.0)
Requires-Dist: mkdocs-awesome-pages-plugin (>=2.9.3,<3.0.0)
Requires-Dist: mkdocs-material (>=9.5.40,<10.0.0)
Requires-Dist: pymatgen (>=2024.10.3,<2025.0.0)
Requires-Dist: pytest (>=8.3.3,<9.0.0)
Requires-Dist: rdfpy (>=1.0.0,<2.0.0)
